<PAMDataset>
  <Metadata domain="Esri">
    <MDI key="PyramidResamplingType">NEAREST</MDI>
  </Metadata>
  <PAMRasterBand band="1">
    <Description>Layer_1</Description>
    <Metadata domain="IMAGE_STRUCTURE">
      <MDI key="COMPRESSION">RLE</MDI>
    </Metadata>
    <Metadata>
      <MDI key="LAYER_TYPE">athematic</MDI>
      <MDI key="STATISTICS_EXCLUDEDVALUES"></MDI>
      <MDI key="STATISTICS_HISTOBINVALUES">33072|2462|1388|1097|907|824|823|733|611|509|428|373|354|342|342|296|293|255|262|236|251|219|235|210|208|162|129|124|128|121|119|100|116|119|117|99|112|96|99|81|81|93|73|70|74|72|65|64|55|46|46|35|41|37|42|40|43|24|38|31|33|35|31|31|44|36|42|31|34|31|27|33|23|42|34|35|23|30|26|30|34|20|21|21|23|14|18|14|25|14|13|26|12|16|22|16|11|13|13|7|17|15|9|11|21|12|13|13|7|12|17|9|10|12|4|12|12|10|4|5|7|12|8|7|3|5|6|8|11|8|9|4|8|6|7|1|4|5|2|2|4|2|2|2|3|3|1|2|0|1|0|1|1|1|0|3|0|1|0|1|1|0|1|0|0|0|0|1|0|0|0|0|0|1|1|1|0|0|0|0|0|1|1|0|0|0|0|0|0|0|0|0|0|1|1|0|1|0|0|1|0|0|0|0|0|0|0|0|0|1|0|0|0|0|0|0|0|0|0|0|0|0|0|0|0|1|0|0|0|0|0|0|0|0|0|0|0|0|0|0|0|0|0|0|0|0|0|0|0|0|0|0|0|0|0|1|</MDI>
      <MDI key="STATISTICS_HISTOMAX">434.02508014561</MDI>
      <MDI key="STATISTICS_HISTOMIN">7.8076756171441e-10</MDI>
      <MDI key="STATISTICS_HISTONUMBINS">256</MDI>
      <MDI key="STATISTICS_MAXIMUM">434.02508014561</MDI>
      <MDI key="STATISTICS_MEAN">11.163933524829</MDI>
      <MDI key="STATISTICS_MEDIAN">0</MDI>
      <MDI key="STATISTICS_MINIMUM">7.8076755102446e-10</MDI>
      <MDI key="STATISTICS_MODE">0</MDI>
      <MDI key="STATISTICS_SKIPFACTORX">1</MDI>
      <MDI key="STATISTICS_SKIPFACTORY">1</MDI>
      <MDI key="STATISTICS_STDDEV">29.304380618598</MDI>
    </Metadata>
  </PAMRasterBand>
</PAMDataset>
